intervalpy/__init__.py
intervalpy/interval.py
intervalpy/util.py
intervalpy-0.1.0.dist-info/entry_points.txt
intervalpy-0.1.0.dist-info/LICENSE
intervalpy-0.1.0.dist-info/WHEEL
intervalpy-0.1.0.dist-info/METADATA
intervalpy-0.1.0.dist-info/RECORD
