Metadata-Version: 2.1
Name: intervalpy
Version: 0.1.0
Summary: An interval set utility library.
Home-page: https://github.com/diatche/intervalpy
License: MIT
Keywords: interval,set
Author: Pavel Diatchenko
Author-email: diatche@gmail.com
Requires-Python: >=3.5,<4
Classifier: License :: OSI Approved :: MIT License
Classifier: Programming Language :: Python :: 3
Classifier: Programming Language :: Python :: 3.5
Classifier: Programming Language :: Python :: 3.6
Classifier: Programming Language :: Python :: 3.7
Classifier: Programming Language :: Python :: 3.8
Classifier: Programming Language :: Python :: 3.9
Requires-Dist: toml (>=0.9,<0.10)
Project-URL: Repository, https://github.com/diatche/intervalpy
